concepcy/__init__.py
concepcy/utils/__init__.py
concepcy/utils/parser.py
concepcy/utils/types.py
concepcy-0.1.0.dist-info/WHEEL
concepcy-0.1.0.dist-info/METADATA
concepcy-0.1.0.dist-info/RECORD
