Metadata-Version: 2.1
Name: concepcy
Version: 0.1.0
Summary: 💫 SpaCy wrapper for ConceptNet 💫
Home-page: https://github.com/JulesBelveze/concepcy
Keywords: nlp,spacy,conceptnet
Author: JulesBelveze
Author-email: jules.belveze@hotmail.fr
Requires-Python: >=3.8,<4.0
Classifier: Programming Language :: Python :: 3
Classifier: Programming Language :: Python :: 3.10
Classifier: Programming Language :: Python :: 3.8
Classifier: Programming Language :: Python :: 3.9
Classifier: Topic :: Scientific/Engineering :: Artificial Intelligence
Classifier: Topic :: Text Processing
Requires-Dist: pydantic (>=1.9.1,<2.0.0)
Requires-Dist: request-boost (>=0.6,<0.7)
Requires-Dist: spacy (>=3.3.0,<4.0.0)
Project-URL: Repository, https://github.com/JulesBelveze/concepcy
